[
    {
        "id": 1,
        "title": "极域工具合集",
        "excerpt": "有关破解极域电子教室的工具合集",
        "date": "2025-03-15",
        "url": "https://jiyukiller.github.io/",
        "tags": [
            "计算机",
            "破解"
        ]
    },
    {
        "id": 2,
        "title": "MC生存整合包2.0(1.19.2)",
        "excerpt": "将Mod和光影整合在了一起(还有人看吗...)",
        "date": "2025-05-11",
        "url": "https://cccimg.com/down.php/2a29d60d3935f3503d63c8219d840395.zip&DJY",
        "tags": [
            "我的世界",
            "整合包"
        ]
    },
    {
        "id": 3,
        "title": "A Real Me",
        "excerpt": "我们致力于设计并开发原创、高品质、具时效性的各类有趣及有价值的测试产品。其范围包括但不限于心理性格、智力与各类知识、人际关系、影视文学作品角色等。我们希望通过这些测试，您可以感到快乐，收获知识，更可以进一步了解自己。",
        "date": "2025-05-11",
        "url": "https://www.arealme.com/cn",
        "tags": [
            "我的世界",
            "整合包"
        ]
    }
]